aioworkers_prometheus/__init__.py
aioworkers_prometheus/config.ini
aioworkers_prometheus/metric.py
aioworkers_prometheus/registry.py
aioworkers_prometheus/service.py
aioworkers_prometheus/version.py
aioworkers_prometheus-0.5.1.dist-info/LICENSE
aioworkers_prometheus-0.5.1.dist-info/METADATA
aioworkers_prometheus-0.5.1.dist-info/WHEEL
aioworkers_prometheus-0.5.1.dist-info/top_level.txt
aioworkers_prometheus-0.5.1.dist-info/RECORD
