Metadata-Version: 2.1
Name: aioworkers-prometheus
Version: 0.5.1
Summary: aioworkers prometheus integration
Home-page: https://github.com/aioworkers/aioworkers-prometheus
Author: Alexander Malev
Author-email: aamalev@gmail.com
License: Apache Software License 2.0
Keywords: aioworkers prometheus
Classifier: Development Status :: 5 - Production/Stable
Classifier: Intended Audience :: Developers
Classifier: Framework :: AsyncIO
Classifier: License :: OSI Approved :: Apache Software License
Classifier: Programming Language :: Python :: 3 :: Only
Classifier: Programming Language :: Python :: 3
Classifier: Programming Language :: Python :: 3.7
Classifier: Programming Language :: Python :: 3.8
Classifier: Programming Language :: Python :: 3.9
Classifier: Programming Language :: Python :: 3.10
Classifier: Programming Language :: Python :: Implementation :: CPython
Classifier: Programming Language :: Python :: Implementation :: PyPy
Requires-Python: >=3.7
License-File: LICENSE
Requires-Dist: aioworkers (>=0.12.0)
Requires-Dist: prometheus-client
